omtestingpackage/__init__.py
omtestingpackage/f1.py
omtestingpackage/extras/__init__.py
omtestingpackage/extras/f2.py
omtestingpackage-0.0.7.dist-info/METADATA
omtestingpackage-0.0.7.dist-info/WHEEL
omtestingpackage-0.0.7.dist-info/top_level.txt
omtestingpackage-0.0.7.dist-info/RECORD
